test_publish_pypi/__init__.py
test_publish_pypi/main.py
test_publish_pypi-0.16.0.dist-info/METADATA
test_publish_pypi-0.16.0.dist-info/WHEEL
test_publish_pypi-0.16.0.dist-info/entry_points.txt
test_publish_pypi-0.16.0.dist-info/RECORD
